{
  "ComponentIndexes": {},
  "ControlUniqueGuids": {},
  "ControlUniqueIds": {
    "App": 1,
    "Attachments_DataCard1": 309,
    "Bus Services Request": 562,
    "Button1": 470,
    "Button2": 463,
    "Button2_1": 10,
    "Button3": 136,
    "Button3_1": 137,
    "Button3_4": 64,
    "Button3_5": 65,
    "Button4": 558,
    "Button4_1": 714,
    "Button5": 477,
    "Button5_1": 478,
    "Button6": 561,
    "Canvas1": 634,
    "Canvas1_1": 525,
    "Canvas1_2": 681,
    "Canvas2": 405,
    "CC:Centro de Costos_DataCard1": 365,
    "CC_DataCard1": 360,
    "CedulaFJ_DataCard1": 385,
    "Check_DataCard1": 345,
    "Checkbox2": 426,
    "Checkbox2_1": 427,
    "Checkbox2_2": 428,
    "Checkbox2_3": 429,
    "Citizenship_Column1": 32,
    "Citizenship_DataCard1": 209,
    "ComboBox1": 647,
    "ComboBox1_1": 653,
    "ComboBox1_2": 648,
    "ComboBox2": 416,
    "ComboBox2_1": 420,
    "ComboBox3": 536,
    "ComboBox4": 15,
    "Comentario_DataCard1": 620,
    "Comentarios_DataCard2": 112,
    "Comments on Timing_Column1": 38,
    "Comments on Timing_DataCard1": 239,
    "Company's Name_Column1": 20,
    "Company's Name_DataCard1": 149,
    "Consecutivo_Column1": 17,
    "Consecutivo_Columna1": 52,
    "Consecutivo_DataCard1": 289,
    "Consecutivo_DataCard3": 117,
    "ContractList": 16,
    "ContractRequest": 131,
    "Contractual Relation (Class Teaching)_Column1": 28,
    "Contractual Relation (Class Teaching)_DataCard1": 189,
    "Contractual Relation_Column1": 27,
    "Contractual Relation_DataCard1": 184,
    "CreditCard_DataCard1": 335,
    "Currency_Column1": 42,
    "Currency_DataCard1": 259,
    "Daily Rate_Column1": 44,
    "Daily Rate_DataCard1": 269,
    "DataCard1": 635,
    "DataCard1_1": 526,
    "DataCard1_2": 682,
    "DataCard2": 657,
    "DataCard2_1": 537,
    "DataCard2_2": 693,
    "DataCard3": 555,
    "DataCard3_1": 711,
    "DataCard4": 406,
    "DataCard5": 437,
    "DataCardKey1": 141,
    "DataCardKey10": 186,
    "DataCardKey100": 124,
    "DataCardKey102": 607,
    "DataCardKey11": 191,
    "DataCardKey12": 196,
    "DataCardKey13": 201,
    "DataCardKey14": 206,
    "DataCardKey15": 211,
    "DataCardKey16": 216,
    "DataCardKey17": 221,
    "DataCardKey18": 226,
    "DataCardKey19": 231,
    "DataCardKey2": 146,
    "DataCardKey20": 236,
    "DataCardKey21": 241,
    "DataCardKey22": 246,
    "DataCardKey23": 251,
    "DataCardKey24": 256,
    "DataCardKey25": 261,
    "DataCardKey26": 266,
    "DataCardKey27": 271,
    "DataCardKey28": 276,
    "DataCardKey29": 281,
    "DataCardKey3": 151,
    "DataCardKey30": 291,
    "DataCardKey31": 311,
    "DataCardKey32": 286,
    "DataCardKey33": 296,
    "DataCardKey34": 342,
    "DataCardKey35": 301,
    "DataCardKey36": 306,
    "DataCardKey37": 347,
    "DataCardKey38": 322,
    "DataCardKey39": 327,
    "DataCardKey4": 156,
    "DataCardKey40": 332,
    "DataCardKey41": 337,
    "DataCardKey42": 352,
    "DataCardKey43": 357,
    "DataCardKey44": 362,
    "DataCardKey45": 367,
    "DataCardKey46": 372,
    "DataCardKey47": 377,
    "DataCardKey48": 382,
    "DataCardKey49": 387,
    "DataCardKey5": 161,
    "DataCardKey50": 392,
    "DataCardKey51": 397,
    "DataCardKey52": 484,
    "DataCardKey53": 489,
    "DataCardKey54": 509,
    "DataCardKey55": 499,
    "DataCardKey56": 494,
    "DataCardKey57": 504,
    "DataCardKey58": 514,
    "DataCardKey59": 519,
    "DataCardKey6": 166,
    "DataCardKey60": 670,
    "DataCardKey7": 176,
    "DataCardKey79": 575,
    "DataCardKey8": 181,
    "DataCardKey80": 580,
    "DataCardKey81": 591,
    "DataCardKey82": 602,
    "DataCardKey84": 612,
    "DataCardKey85": 617,
    "DataCardKey86": 622,
    "DataCardKey88": 627,
    "DataCardKey89": 69,
    "DataCardKey9": 171,
    "DataCardKey90": 74,
    "DataCardKey91": 79,
    "DataCardKey92": 84,
    "DataCardKey93": 89,
    "DataCardKey94": 94,
    "DataCardKey95": 99,
    "DataCardKey96": 104,
    "DataCardKey97": 109,
    "DataCardKey98": 114,
    "DataCardKey99": 119,
    "DataCardValue1": 142,
    "DataCardValue10": 187,
    "DataCardValue100": 608,
    "DataCardValue11": 192,
    "DataCardValue12": 197,
    "DataCardValue13": 202,
    "DataCardValue14": 207,
    "DataCardValue15": 212,
    "DataCardValue16": 217,
    "DataCardValue17": 222,
    "DataCardValue18": 227,
    "DataCardValue19": 232,
    "DataCardValue2": 147,
    "DataCardValue20": 237,
    "DataCardValue21": 242,
    "DataCardValue22": 247,
    "DataCardValue23": 252,
    "DataCardValue24": 257,
    "DataCardValue25": 262,
    "DataCardValue26": 267,
    "DataCardValue27": 272,
    "DataCardValue28": 674,
    "DataCardValue29": 282,
    "DataCardValue3": 152,
    "DataCardValue30": 292,
    "DataCardValue31": 312,
    "DataCardValue32": 287,
    "DataCardValue33": 297,
    "DataCardValue34": 343,
    "DataCardValue35": 302,
    "DataCardValue36": 676,
    "DataCardValue37": 348,
    "DataCardValue38": 323,
    "DataCardValue39": 328,
    "DataCardValue4": 157,
    "DataCardValue40": 333,
    "DataCardValue41": 338,
    "DataCardValue42": 353,
    "DataCardValue43": 358,
    "DataCardValue44": 363,
    "DataCardValue45": 368,
    "DataCardValue46": 373,
    "DataCardValue47": 378,
    "DataCardValue48": 383,
    "DataCardValue49": 388,
    "DataCardValue5": 162,
    "DataCardValue50": 393,
    "DataCardValue51": 398,
    "DataCardValue52": 482,
    "DataCardValue53": 487,
    "DataCardValue54": 507,
    "DataCardValue55": 497,
    "DataCardValue56": 492,
    "DataCardValue57": 502,
    "DataCardValue58": 512,
    "DataCardValue59": 517,
    "DataCardValue6": 167,
    "DataCardValue60": 671,
    "DataCardValue7": 177,
    "DataCardValue79": 576,
    "DataCardValue8": 182,
    "DataCardValue80": 603,
    "DataCardValue82": 613,
    "DataCardValue83": 618,
    "DataCardValue84": 623,
    "DataCardValue86": 628,
    "DataCardValue87": 70,
    "DataCardValue88": 75,
    "DataCardValue89": 80,
    "DataCardValue9": 172,
    "DataCardValue90": 85,
    "DataCardValue91": 90,
    "DataCardValue92": 95,
    "DataCardValue93": 100,
    "DataCardValue94": 105,
    "DataCardValue95": 110,
    "DataCardValue96": 115,
    "DataCardValue97": 120,
    "DataCardValue98": 125,
    "Date of Birth_Column1": 34,
    "Date of Birth_DataCard1": 219,
    "DatePicker1": 549,
    "DatePicker1_1": 550,
    "DatePicker1_2": 705,
    "DatePicker1_3": 706,
    "DatePicker2": 418,
    "DateRequest_Columna1": 54,
    "DateValue1": 584,
    "DateValue2": 595,
    "Datos adjuntos_DataCard1": 395,
    "Datos adjuntos_DataCard2": 625,
    "Datos adjuntos_DataCard3": 122,
    "Deparment/Unit_Columna1": 55,
    "DepartamentoUnidad_DataCard2": 72,
    "Department_Column1": 50,
    "Department_DataCard1": 284,
    "Department_Head_Columna1": 56,
    "Description_Column1": 29,
    "Description_DataCard1": 194,
    "DetailEquimentExternal": 677,
    "Direccion_DataCard1": 506,
    "DireccionPuntoDestino_DataCard2": 97,
    "DireccionPuntoDestino_DataCard3": 605,
    "DireccionPuntoSalida_DataCard1": 600,
    "DireccionPuntoSalida_DataCard2": 92,
    "Dropdown1": 414,
    "Dropdown1_1": 431,
    "Email Address_Column1": 25,
    "Email Address_DataCard1": 179,
    "End Date of Services_Column1": 37,
    "End Date of Services_DataCard1": 234,
    "Entrega_DataCard1": 511,
    "EquipmentList": 51,
    "ErrorMessage1": 143,
    "ErrorMessage10": 188,
    "ErrorMessage100": 126,
    "ErrorMessage11": 193,
    "ErrorMessage12": 198,
    "ErrorMessage13": 203,
    "ErrorMessage14": 208,
    "ErrorMessage15": 213,
    "ErrorMessage16": 218,
    "ErrorMessage17": 223,
    "ErrorMessage18": 228,
    "ErrorMessage19": 233,
    "ErrorMessage2": 148,
    "ErrorMessage20": 238,
    "ErrorMessage21": 243,
    "ErrorMessage22": 248,
    "ErrorMessage23": 253,
    "ErrorMessage24": 258,
    "ErrorMessage25": 263,
    "ErrorMessage26": 268,
    "ErrorMessage27": 273,
    "ErrorMessage28": 278,
    "ErrorMessage29": 283,
    "ErrorMessage3": 153,
    "ErrorMessage30": 293,
    "ErrorMessage31": 313,
    "ErrorMessage32": 288,
    "ErrorMessage33": 298,
    "ErrorMessage34": 344,
    "ErrorMessage35": 303,
    "ErrorMessage36": 308,
    "ErrorMessage37": 349,
    "ErrorMessage38": 324,
    "ErrorMessage39": 329,
    "ErrorMessage4": 158,
    "ErrorMessage40": 334,
    "ErrorMessage41": 339,
    "ErrorMessage42": 354,
    "ErrorMessage43": 359,
    "ErrorMessage44": 364,
    "ErrorMessage45": 369,
    "ErrorMessage46": 374,
    "ErrorMessage47": 379,
    "ErrorMessage48": 384,
    "ErrorMessage49": 389,
    "ErrorMessage5": 163,
    "ErrorMessage50": 394,
    "ErrorMessage51": 399,
    "ErrorMessage52": 485,
    "ErrorMessage53": 490,
    "ErrorMessage54": 510,
    "ErrorMessage55": 500,
    "ErrorMessage56": 495,
    "ErrorMessage57": 505,
    "ErrorMessage58": 515,
    "ErrorMessage59": 520,
    "ErrorMessage6": 168,
    "ErrorMessage60": 672,
    "ErrorMessage7": 178,
    "ErrorMessage79": 577,
    "ErrorMessage8": 183,
    "ErrorMessage80": 588,
    "ErrorMessage81": 599,
    "ErrorMessage82": 604,
    "ErrorMessage82_1": 609,
    "ErrorMessage84": 614,
    "ErrorMessage85": 619,
    "ErrorMessage86": 624,
    "ErrorMessage88": 629,
    "ErrorMessage89": 71,
    "ErrorMessage9": 173,
    "ErrorMessage90": 76,
    "ErrorMessage91": 81,
    "ErrorMessage92": 86,
    "ErrorMessage93": 91,
    "ErrorMessage94": 96,
    "ErrorMessage95": 101,
    "ErrorMessage96": 106,
    "ErrorMessage97": 111,
    "ErrorMessage98": 116,
    "ErrorMessage99": 121,
    "Espaciado": 655,
    "ExtensionAddendumContract": 127,
    "External_Location_Columna1": 57,
    "Fax Number_Column1": 24,
    "Fax Number_DataCard1": 174,
    "FechaFinal_DataCard1": 589,
    "FechaFinal_DataCard2": 87,
    "FechaInicio_DataCard1": 578,
    "FechaInicio_DataCard2": 82,
    "First Name_Column1": 18,
    "Form1": 138,
    "Form1_1": 572,
    "Form1_2": 66,
    "Form2": 319,
    "Form2_1": 480,
    "Funded by_Column1": 48,
    "Funded by_DataCard1": 304,
    "Gallery1_1": 661,
    "Gallery1_2": 544,
    "Gallery1_3": 445,
    "Gallery1_4": 700,
    "Gallery3": 461,
    "galleryTemplate1": 9,
    "galleryTemplate1_1": 662,
    "galleryTemplate1_2": 545,
    "galleryTemplate1_3": 446,
    "galleryTemplate1_4": 701,
    "galleryTemplate3": 462,
    "Gender_Column1": 22,
    "Gender_DataCard1": 159,
    "Home": 467,
    "HomeIconList": 6,
    "HorarioEmpresa_DataCard1": 491,
    "HourValue1": 585,
    "HourValue2": 596,
    "Icon1": 633,
    "Icon1_1": 134,
    "Icon1_10": 63,
    "Icon1_11": 403,
    "Icon1_12": 404,
    "Icon1_13": 475,
    "Icon1_14": 476,
    "Icon1_15": 680,
    "Icon1_2": 135,
    "Icon1_3": 524,
    "Icon1_4": 130,
    "Icon1_5": 317,
    "Icon1_6": 318,
    "Icon1_7": 565,
    "Icon1_8": 566,
    "Icon1_9": 62,
    "Icon2": 666,
    "Icon2_1": 667,
    "Icon2_2": 552,
    "Icon2_3": 553,
    "Icon2_4": 447,
    "Icon2_5": 454,
    "Icon3": 459,
    "Icon4": 460,
    "Identification Number_Column1": 30,
    "Identification Number_DataCard1": 199,
    "Image1": 636,
    "Image1_1": 527,
    "Image1_2": 683,
    "Image2": 465,
    "Image3": 12,
    "Image7": 407,
    "Institucional Vehicle Request": 59,
    "International_DataCard1": 355,
    "InvoiceN_DataCard1": 380,
    "Is_Juridical_DataCard1": 669,
    "Juridical Number_Column1": 31,
    "Juridical Number_DataCard1": 204,
    "Label1": 637,
    "Label1_1": 528,
    "Label1_2": 684,
    "Label10": 569,
    "Label10_1": 571,
    "Label10_2": 568,
    "Label11": 581,
    "Label11_1": 582,
    "Label11_2": 583,
    "Label11_3": 592,
    "Label11_4": 593,
    "Label11_5": 594,
    "Label12": 409,
    "Label12_1": 413,
    "Label12_2": 411,
    "Label12_3": 415,
    "Label12_4": 417,
    "Label12_5": 419,
    "Label12_6": 425,
    "Label12_7": 430,
    "Label12_8": 432,
    "Label12_9": 435,
    "Label13": 408,
    "Label13_1": 434,
    "Label14": 421,
    "Label14_1": 422,
    "Label14_2": 423,
    "Label14_3": 424,
    "Label15": 479,
    "Label16": 529,
    "Label16_1": 530,
    "Label16_10": 688,
    "Label16_11": 689,
    "Label16_12": 690,
    "Label16_13": 691,
    "Label16_14": 719,
    "Label16_2": 531,
    "Label16_3": 532,
    "Label16_4": 533,
    "Label16_5": 534,
    "Label16_6": 535,
    "Label16_7": 685,
    "Label16_8": 686,
    "Label16_9": 687,
    "Label17": 11,
    "Label17_1": 466,
    "Label2": 644,
    "Label2_1": 646,
    "Label2_2": 652,
    "Label2_3": 638,
    "Label2_4": 639,
    "Label2_5": 640,
    "Label2_6": 651,
    "Label2_7": 645,
    "Label3": 650,
    "Label4": 468,
    "Label5": 556,
    "Label5_1": 557,
    "Label5_2": 712,
    "Label5_3": 713,
    "Label6": 464,
    "Label7": 471,
    "Label8": 448,
    "Label9": 570,
    "Label9_1": 567,
    "Last Name_Column1": 19,
    "Last Name_DataCard1": 144,
    "LblAppName1": 632,
    "LblAppName1_1": 458,
    "LblAppName1_10": 679,
    "LblAppName1_2": 133,
    "LblAppName1_3": 523,
    "LblAppName1_4": 129,
    "LblAppName1_5": 316,
    "LblAppName1_6": 5,
    "LblAppName1_7": 564,
    "LblAppName1_8": 61,
    "LblAppName1_9": 474,
    "LblAppName2": 402,
    "LblAppName2_1": 439,
    "List": 3,
    "MaestriaSolicitaServicio_DataCard1": 107,
    "MaestriaSolicitudServicio_DataCard1": 615,
    "Master Degree_Column1": 49,
    "Master Degree_DataCard1": 299,
    "Menu": 456,
    "MenuIcon": 7,
    "MinuteValue1": 587,
    "MinuteValue2": 598,
    "Name_DataCard1": 375,
    "NameSolicitor_Columna1": 53,
    "National_DataCard1": 350,
    "NavMenuList": 8,
    "NombreEmpresa_DataCard1": 486,
    "NombreJefe_DataCard1": 573,
    "NombreJefe_DataCard2": 77,
    "NumeroPersonas_DataCard1": 610,
    "NumeroPersonas_DataCard2": 102,
    "Other Payment Plan_Column1": 41,
    "Other Payment Plan_DataCard1": 254,
    "Payment Plan_Column1": 40,
    "Payment Plan_DataCard1": 249,
    "Payment Rate_Column1": 39,
    "Payment Rate_DataCard1": 244,
    "Payment schedule proposed_Column1": 47,
    "Payment schedule proposed_DataCard1": 294,
    "PaymentRequest": 314,
    "Permanent Residence Addresss_Column1": 26,
    "Permanent Residence Addresss_DataCard1": 169,
    "PersonaContactar_DataCard1": 501,
    "PettyCash_DataCard1": 330,
    "Place will stay_Column1": 45,
    "Place will stay_DataCard1": 274,
    "Preferred Payment Method_Column1": 35,
    "Preferred Payment Method_DataCard1": 224,
    "PurchaseRequest": 630,
    "Purpose_Columna1": 58,
    "RectQuickActionBar1": 631,
    "RectQuickActionBar1_1": 457,
    "RectQuickActionBar1_2": 522,
    "RectQuickActionBar1_3": 4,
    "RectQuickActionBar1_4": 678,
    "RectQuickActionBar2": 132,
    "RectQuickActionBar2_1": 128,
    "RectQuickActionBar2_2": 315,
    "RectQuickActionBar2_3": 563,
    "RectQuickActionBar2_4": 60,
    "RectQuickActionBar2_5": 473,
    "RectQuickActionBar3": 401,
    "RectQuickActionBar3_1": 438,
    "Relacion_DataCard1": 390,
    "Representative´s Name_Column1": 21,
    "Representative´s Name_DataCard1": 154,
    "RequestEquimentExternal": 521,
    "Retiro_DataCard1": 516,
    "Separator1": 586,
    "Separator2": 597,
    "Separator2_1": 668,
    "Separator2_2": 554,
    "Separator2_3": 455,
    "Separator2_4": 710,
    "SIMPE_DataCard1": 325,
    "SolicitudMandados": 472,
    "Start date of services_Column1": 36,
    "Start date of services_DataCard1": 229,
    "StarVisible1": 140,
    "StarVisible10": 185,
    "StarVisible100": 123,
    "StarVisible102": 606,
    "StarVisible11": 190,
    "StarVisible12": 195,
    "StarVisible13": 200,
    "StarVisible14": 205,
    "StarVisible15": 210,
    "StarVisible16": 215,
    "StarVisible17": 220,
    "StarVisible18": 225,
    "StarVisible19": 230,
    "StarVisible2": 145,
    "StarVisible20": 235,
    "StarVisible21": 240,
    "StarVisible22": 245,
    "StarVisible23": 250,
    "StarVisible24": 255,
    "StarVisible25": 260,
    "StarVisible26": 265,
    "StarVisible27": 270,
    "StarVisible28": 275,
    "StarVisible29": 280,
    "StarVisible3": 150,
    "StarVisible30": 290,
    "StarVisible31": 310,
    "StarVisible32": 285,
    "StarVisible33": 295,
    "StarVisible34": 341,
    "StarVisible35": 300,
    "StarVisible36": 305,
    "StarVisible37": 346,
    "StarVisible38": 321,
    "StarVisible39": 326,
    "StarVisible4": 155,
    "StarVisible40": 331,
    "StarVisible41": 336,
    "StarVisible42": 351,
    "StarVisible43": 356,
    "StarVisible44": 361,
    "StarVisible45": 366,
    "StarVisible46": 371,
    "StarVisible47": 376,
    "StarVisible48": 381,
    "StarVisible49": 386,
    "StarVisible5": 160,
    "StarVisible50": 391,
    "StarVisible51": 396,
    "StarVisible52": 483,
    "StarVisible53": 488,
    "StarVisible54": 508,
    "StarVisible55": 498,
    "StarVisible56": 493,
    "StarVisible57": 503,
    "StarVisible58": 513,
    "StarVisible59": 518,
    "StarVisible6": 165,
    "StarVisible60": 673,
    "StarVisible7": 175,
    "StarVisible79": 574,
    "StarVisible8": 180,
    "StarVisible80": 579,
    "StarVisible81": 590,
    "StarVisible82": 601,
    "StarVisible84": 611,
    "StarVisible85": 616,
    "StarVisible86": 621,
    "StarVisible88": 626,
    "StarVisible89": 68,
    "StarVisible9": 170,
    "StarVisible90": 73,
    "StarVisible91": 78,
    "StarVisible92": 83,
    "StarVisible93": 88,
    "StarVisible94": 93,
    "StarVisible95": 98,
    "StarVisible96": 103,
    "StarVisible97": 108,
    "StarVisible98": 113,
    "StarVisible99": 118,
    "State_Columna1": 720,
    "Teaching Days_Column1": 33,
    "Teaching Days_DataCard1": 214,
    "TelefonoEmpresa_DataCard1": 496,
    "Telephone Number_Column1": 23,
    "Telephone Number_DataCard1": 164,
    "TextInput1": 410,
    "TextInput1_1": 412,
    "TextInput1_2": 433,
    "TextInput2": 658,
    "TextInput2_1": 659,
    "TextInput2_10": 441,
    "TextInput2_11": 442,
    "TextInput2_12": 443,
    "TextInput2_13": 444,
    "TextInput2_14": 694,
    "TextInput2_15": 695,
    "TextInput2_16": 696,
    "TextInput2_17": 697,
    "TextInput2_18": 698,
    "TextInput2_19": 699,
    "TextInput2_2": 660,
    "TextInput2_3": 538,
    "TextInput2_4": 539,
    "TextInput2_5": 540,
    "TextInput2_6": 541,
    "TextInput2_7": 542,
    "TextInput2_8": 543,
    "TextInput2_9": 440,
    "TextInput3": 663,
    "TextInput3_1": 664,
    "TextInput3_10": 453,
    "TextInput3_11": 452,
    "TextInput3_12": 702,
    "TextInput3_13": 703,
    "TextInput3_14": 704,
    "TextInput3_15": 707,
    "TextInput3_2": 665,
    "TextInput3_3": 546,
    "TextInput3_4": 547,
    "TextInput3_5": 548,
    "TextInput3_6": 449,
    "TextInput3_7": 551,
    "TextInput3_8": 450,
    "TextInput3_9": 451,
    "TextInput4": 469,
    "TextInput5": 559,
    "TextInput5_1": 560,
    "TextInput5_2": 715,
    "TextInput5_3": 716,
    "TextInput6": 436,
    "TextInput7": 649,
    "TextInput7_1": 641,
    "TextInput7_2": 642,
    "TextInput7_3": 643,
    "TextInput7_4": 656,
    "TextInput7_5": 654,
    "TextInput8": 14,
    "TipoPayment_DataCard1": 370,
    "Title_DataCard1": 139,
    "Title_DataCard2": 340,
    "Title_DataCard3": 481,
    "Title_DataCard5": 67,
    "Title1": 13,
    "Total_Column1": 46,
    "Total_DataCard1": 279,
    "Traveling_Column1": 43,
    "Traveling_DataCard1": 264,
    "TravelRequest": 400,
    "Wire Transfer_DataCard1": 320
  },
  "FunctionParamsInvariantScripts": {},
  "FunctionParamsInvariantScriptsOnInstances": {},
  "HeaderLastSavedDateTimeUTC": "08/25/2022 20:29:02",
  "IsLegacyComponentAllowGlobalScopeCase": false,
  "LocalConnectionIDReferences": {
    "18b02a7e-3e00-47af-8d7f-a6f3704e5983": "\"/providers/microsoft.powerapps/apis/shared_sharepointonline/connections/shared-sharepointonl-637a787e-5558-4f71-bed2-b646d602306e\"",
    "8f830dd5-144b-4629-89d4-2cd185de289f": "\"/providers/microsoft.powerapps/apis/shared_office365users/connections/6caafe1b70ea4390a115ea656ed2761d\""
  },
  "LocalDatabaseReferencesAsEmpty": false,
  "LocalResourceFileNames": {
    "Contratos (6)": "b43f12b2-fe95-4488-8f18-bffc6a231e62.png",
    "Contratos (7)": "d10d2936-c2d4-4d7e-83a9-b9325cb5ded0.png",
    "Contratos (8)": "1f40203a-12ec-423f-9420-69a8d6f199d5.png"
  },
  "LocalResourceRootPaths": {
    "Contratos (6)": "https://docserverpwaprodwus.blob.core.windows.net/0b39aed9-76e8-4403-8772-4f4a21dedcc9-1/resource/Assets0Images0b43f12b2-fe95-4488-8f18-bffc6a231e62.png?sv=2017-04-17&sr=b&sig=Z9XiNKMRhE4x%2BVUlrxozypPoNoDndtWtSic0qG6AwG0%3D&spr=https&se=2022-08-26T16%3A54%3A37Z&sp=r",
    "Contratos (7)": "https://docserverpwaprodwus.blob.core.windows.net/0b39aed9-76e8-4403-8772-4f4a21dedcc9-1/resource/Assets0Images0d10d2936-c2d4-4d7e-83a9-b9325cb5ded0.png?sv=2017-04-17&sr=b&sig=piy8apvkn6aeA%2BmYrSZuPLqBjgUL51Ht4YzgFNylnM4%3D&spr=https&se=2022-08-26T16%3A54%3A37Z&sp=r",
    "Contratos (8)": "https://docserverpwaprodwus.blob.core.windows.net/0b39aed9-76e8-4403-8772-4f4a21dedcc9-1/resource/Assets0Images01f40203a-12ec-423f-9420-69a8d6f199d5.png?sv=2017-04-17&sr=b&sig=bk7aBBCWrJ%2Bep0H0S1X6R0AErMGlAXL%2Bgq2ZCP%2BzSkw%3D&spr=https&se=2022-08-26T16%3A54%3A37Z&sp=r"
  },
  "OrderComponentMetadata": {},
  "OrderComponentTemplate": {},
  "OrderDataSource": {
    "Bus Service": 8,
    "Centro de Costos": 3,
    "ComboBoxSample": 2,
    "Contract Request": 6,
    "CustomGallerySample": 5,
    "Departments": 13,
    "DropDownSample": 4,
    "EFEU": 17,
    "Equipment Assigment": 14,
    "Equipment Request": 15,
    "Payment Request": 7,
    "PSR": 1,
    "PSR_QDJ": 16,
    "Solicitud de mandados": 12,
    "TR": 18,
    "Travel Information": 11,
    "Travel Request": 10,
    "UsuariosdeOffice365": 0,
    "Vehicle Request": 9
  },
  "OrderGroupControls": {},
  "OrderPcfTemplate": {},
  "OrderTemplate": {},
  "OrderXMLTemplate": {
    "attachments": 10,
    "button": 4,
    "checkbox": 15,
    "combobox": 7,
    "datepicker": 9,
    "dropdown": 14,
    "fluidGrid": 13,
    "form": 8,
    "gallery": 3,
    "icon": 2,
    "image": 5,
    "label": 1,
    "rectangle": 0,
    "richTextEditor": 11,
    "text": 6,
    "toggleSwitch": 12
  },
  "PublishOrderIndices": {
    "App": 0,
    "Attachments_DataCard1": 367,
    "Bus Services Request": 0,
    "Button1": 2,
    "Button2": 10,
    "Button2_1": 20,
    "Button3": 189,
    "Button3_1": 190,
    "Button3_4": 443,
    "Button3_5": 444,
    "Button4": 144,
    "Button4_1": 182,
    "Button5": 598,
    "Button5_1": 599,
    "Button6": 147,
    "Canvas1": 73,
    "Canvas1_1": 111,
    "Canvas1_2": 151,
    "Canvas2": 646,
    "CC:Centro de Costos_DataCard1": 559,
    "CC_DataCard1": 554,
    "CedulaFJ_DataCard1": 579,
    "Check_DataCard1": 539,
    "Checkbox2": 667,
    "Checkbox2_1": 668,
    "Checkbox2_2": 669,
    "Checkbox2_3": 670,
    "Citizenship_Column1": 43,
    "Citizenship_DataCard1": 262,
    "ComboBox1": 86,
    "ComboBox1_1": 92,
    "ComboBox1_2": 87,
    "ComboBox2": 657,
    "ComboBox2_1": 661,
    "ComboBox3": 122,
    "ComboBox4": 25,
    "Comentario_DataCard1": 429,
    "Comentarios_DataCard2": 491,
    "Comments on Timing_Column1": 49,
    "Comments on Timing_DataCard1": 292,
    "Company's Name_Column1": 31,
    "Company's Name_DataCard1": 202,
    "Consecutivo_Column1": 27,
    "Consecutivo_Columna1": 63,
    "Consecutivo_DataCard1": 337,
    "Consecutivo_DataCard3": 496,
    "ContractList": 26,
    "ContractRequest": 0,
    "Contractual Relation (Class Teaching)_Column1": 39,
    "Contractual Relation (Class Teaching)_DataCard1": 242,
    "Contractual Relation_Column1": 38,
    "Contractual Relation_DataCard1": 237,
    "CreditCard_DataCard1": 529,
    "Currency_Column1": 53,
    "Currency_DataCard1": 312,
    "Daily Rate_Column1": 55,
    "Daily Rate_DataCard1": 322,
    "DataCard1": 74,
    "DataCard1_1": 112,
    "DataCard1_2": 152,
    "DataCard2": 96,
    "DataCard2_1": 123,
    "DataCard2_2": 163,
    "DataCard3": 141,
    "DataCard3_1": 179,
    "DataCard4": 647,
    "DataCard5": 678,
    "DataCardKey1": 194,
    "DataCardKey10": 239,
    "DataCardKey100": 503,
    "DataCardKey102": 416,
    "DataCardKey11": 244,
    "DataCardKey12": 249,
    "DataCardKey13": 254,
    "DataCardKey14": 259,
    "DataCardKey15": 264,
    "DataCardKey16": 269,
    "DataCardKey17": 274,
    "DataCardKey18": 279,
    "DataCardKey19": 284,
    "DataCardKey2": 199,
    "DataCardKey20": 289,
    "DataCardKey21": 294,
    "DataCardKey22": 299,
    "DataCardKey23": 304,
    "DataCardKey24": 309,
    "DataCardKey25": 314,
    "DataCardKey26": 319,
    "DataCardKey27": 324,
    "DataCardKey28": 354,
    "DataCardKey29": 329,
    "DataCardKey3": 204,
    "DataCardKey30": 339,
    "DataCardKey31": 369,
    "DataCardKey32": 334,
    "DataCardKey33": 344,
    "DataCardKey34": 536,
    "DataCardKey35": 349,
    "DataCardKey36": 359,
    "DataCardKey37": 541,
    "DataCardKey38": 516,
    "DataCardKey39": 521,
    "DataCardKey4": 209,
    "DataCardKey40": 526,
    "DataCardKey41": 531,
    "DataCardKey42": 546,
    "DataCardKey43": 551,
    "DataCardKey44": 556,
    "DataCardKey45": 561,
    "DataCardKey46": 566,
    "DataCardKey47": 571,
    "DataCardKey48": 576,
    "DataCardKey49": 581,
    "DataCardKey5": 214,
    "DataCardKey50": 586,
    "DataCardKey51": 591,
    "DataCardKey52": 605,
    "DataCardKey53": 610,
    "DataCardKey54": 630,
    "DataCardKey55": 620,
    "DataCardKey56": 615,
    "DataCardKey57": 625,
    "DataCardKey58": 635,
    "DataCardKey59": 640,
    "DataCardKey6": 219,
    "DataCardKey60": 364,
    "DataCardKey7": 229,
    "DataCardKey79": 384,
    "DataCardKey8": 234,
    "DataCardKey80": 389,
    "DataCardKey81": 400,
    "DataCardKey82": 411,
    "DataCardKey84": 421,
    "DataCardKey85": 426,
    "DataCardKey86": 431,
    "DataCardKey88": 436,
    "DataCardKey89": 448,
    "DataCardKey9": 224,
    "DataCardKey90": 453,
    "DataCardKey91": 458,
    "DataCardKey92": 463,
    "DataCardKey93": 468,
    "DataCardKey94": 473,
    "DataCardKey95": 478,
    "DataCardKey96": 483,
    "DataCardKey97": 488,
    "DataCardKey98": 493,
    "DataCardKey99": 498,
    "DataCardValue1": 195,
    "DataCardValue10": 240,
    "DataCardValue100": 417,
    "DataCardValue11": 245,
    "DataCardValue12": 250,
    "DataCardValue13": 255,
    "DataCardValue14": 260,
    "DataCardValue15": 265,
    "DataCardValue16": 270,
    "DataCardValue17": 275,
    "DataCardValue18": 280,
    "DataCardValue19": 285,
    "DataCardValue2": 200,
    "DataCardValue20": 290,
    "DataCardValue21": 295,
    "DataCardValue22": 300,
    "DataCardValue23": 305,
    "DataCardValue24": 310,
    "DataCardValue25": 315,
    "DataCardValue26": 320,
    "DataCardValue27": 325,
    "DataCardValue28": 355,
    "DataCardValue29": 330,
    "DataCardValue3": 205,
    "DataCardValue30": 340,
    "DataCardValue31": 370,
    "DataCardValue32": 335,
    "DataCardValue33": 345,
    "DataCardValue34": 537,
    "DataCardValue35": 350,
    "DataCardValue36": 360,
    "DataCardValue37": 542,
    "DataCardValue38": 517,
    "DataCardValue39": 522,
    "DataCardValue4": 210,
    "DataCardValue40": 527,
    "DataCardValue41": 532,
    "DataCardValue42": 547,
    "DataCardValue43": 552,
    "DataCardValue44": 557,
    "DataCardValue45": 562,
    "DataCardValue46": 567,
    "DataCardValue47": 572,
    "DataCardValue48": 577,
    "DataCardValue49": 582,
    "DataCardValue5": 215,
    "DataCardValue50": 587,
    "DataCardValue51": 592,
    "DataCardValue52": 603,
    "DataCardValue53": 608,
    "DataCardValue54": 628,
    "DataCardValue55": 618,
    "DataCardValue56": 613,
    "DataCardValue57": 623,
    "DataCardValue58": 633,
    "DataCardValue59": 638,
    "DataCardValue6": 220,
    "DataCardValue60": 365,
    "DataCardValue7": 230,
    "DataCardValue79": 385,
    "DataCardValue8": 235,
    "DataCardValue80": 412,
    "DataCardValue82": 422,
    "DataCardValue83": 427,
    "DataCardValue84": 432,
    "DataCardValue86": 437,
    "DataCardValue87": 449,
    "DataCardValue88": 454,
    "DataCardValue89": 459,
    "DataCardValue9": 225,
    "DataCardValue90": 464,
    "DataCardValue91": 469,
    "DataCardValue92": 474,
    "DataCardValue93": 479,
    "DataCardValue94": 484,
    "DataCardValue95": 489,
    "DataCardValue96": 494,
    "DataCardValue97": 499,
    "DataCardValue98": 504,
    "Date of Birth_Column1": 45,
    "Date of Birth_DataCard1": 272,
    "DatePicker1": 135,
    "DatePicker1_1": 136,
    "DatePicker1_2": 175,
    "DatePicker1_3": 176,
    "DatePicker2": 659,
    "DateRequest_Columna1": 65,
    "DateValue1": 393,
    "DateValue2": 404,
    "Datos adjuntos_DataCard1": 589,
    "Datos adjuntos_DataCard2": 434,
    "Datos adjuntos_DataCard3": 501,
    "Deparment/Unit_Columna1": 66,
    "DepartamentoUnidad_DataCard2": 451,
    "Department_Column1": 61,
    "Department_DataCard1": 332,
    "Department_Head_Columna1": 67,
    "Description_Column1": 40,
    "Description_DataCard1": 247,
    "DetailEquimentExternal": 0,
    "Direccion_DataCard1": 627,
    "DireccionPuntoDestino_DataCard2": 476,
    "DireccionPuntoDestino_DataCard3": 414,
    "DireccionPuntoSalida_DataCard1": 409,
    "DireccionPuntoSalida_DataCard2": 471,
    "Dropdown1": 655,
    "Dropdown1_1": 672,
    "Email Address_Column1": 36,
    "Email Address_DataCard1": 232,
    "End Date of Services_Column1": 48,
    "End Date of Services_DataCard1": 287,
    "Entrega_DataCard1": 632,
    "EquipmentList": 62,
    "ErrorMessage1": 196,
    "ErrorMessage10": 241,
    "ErrorMessage100": 505,
    "ErrorMessage11": 246,
    "ErrorMessage12": 251,
    "ErrorMessage13": 256,
    "ErrorMessage14": 261,
    "ErrorMessage15": 266,
    "ErrorMessage16": 271,
    "ErrorMessage17": 276,
    "ErrorMessage18": 281,
    "ErrorMessage19": 286,
    "ErrorMessage2": 201,
    "ErrorMessage20": 291,
    "ErrorMessage21": 296,
    "ErrorMessage22": 301,
    "ErrorMessage23": 306,
    "ErrorMessage24": 311,
    "ErrorMessage25": 316,
    "ErrorMessage26": 321,
    "ErrorMessage27": 326,
    "ErrorMessage28": 356,
    "ErrorMessage29": 331,
    "ErrorMessage3": 206,
    "ErrorMessage30": 341,
    "ErrorMessage31": 371,
    "ErrorMessage32": 336,
    "ErrorMessage33": 346,
    "ErrorMessage34": 538,
    "ErrorMessage35": 351,
    "ErrorMessage36": 361,
    "ErrorMessage37": 543,
    "ErrorMessage38": 518,
    "ErrorMessage39": 523,
    "ErrorMessage4": 211,
    "ErrorMessage40": 528,
    "ErrorMessage41": 533,
    "ErrorMessage42": 548,
    "ErrorMessage43": 553,
    "ErrorMessage44": 558,
    "ErrorMessage45": 563,
    "ErrorMessage46": 568,
    "ErrorMessage47": 573,
    "ErrorMessage48": 578,
    "ErrorMessage49": 583,
    "ErrorMessage5": 216,
    "ErrorMessage50": 588,
    "ErrorMessage51": 593,
    "ErrorMessage52": 606,
    "ErrorMessage53": 611,
    "ErrorMessage54": 631,
    "ErrorMessage55": 621,
    "ErrorMessage56": 616,
    "ErrorMessage57": 626,
    "ErrorMessage58": 636,
    "ErrorMessage59": 641,
    "ErrorMessage6": 221,
    "ErrorMessage60": 366,
    "ErrorMessage7": 231,
    "ErrorMessage79": 386,
    "ErrorMessage8": 236,
    "ErrorMessage80": 397,
    "ErrorMessage81": 408,
    "ErrorMessage82": 413,
    "ErrorMessage82_1": 418,
    "ErrorMessage84": 423,
    "ErrorMessage85": 428,
    "ErrorMessage86": 433,
    "ErrorMessage88": 438,
    "ErrorMessage89": 450,
    "ErrorMessage9": 226,
    "ErrorMessage90": 455,
    "ErrorMessage91": 460,
    "ErrorMessage92": 465,
    "ErrorMessage93": 470,
    "ErrorMessage94": 475,
    "ErrorMessage95": 480,
    "ErrorMessage96": 485,
    "ErrorMessage97": 490,
    "ErrorMessage98": 495,
    "ErrorMessage99": 500,
    "Espaciado": 94,
    "ExtensionAddendumContract": 0,
    "External_Location_Columna1": 68,
    "Fax Number_Column1": 35,
    "Fax Number_DataCard1": 227,
    "FechaFinal_DataCard1": 398,
    "FechaFinal_DataCard2": 466,
    "FechaInicio_DataCard1": 387,
    "FechaInicio_DataCard2": 461,
    "First Name_Column1": 29,
    "Form1": 191,
    "Form1_1": 381,
    "Form1_2": 445,
    "Form2": 513,
    "Form2_1": 601,
    "Funded by_Column1": 59,
    "Funded by_DataCard1": 357,
    "Gallery1_1": 100,
    "Gallery1_2": 130,
    "Gallery1_3": 686,
    "Gallery1_4": 170,
    "Gallery3": 8,
    "galleryTemplate1": 19,
    "galleryTemplate1_1": 101,
    "galleryTemplate1_2": 131,
    "galleryTemplate1_3": 687,
    "galleryTemplate1_4": 171,
    "galleryTemplate3": 9,
    "Gender_Column1": 33,
    "Gender_DataCard1": 212,
    "Home": 0,
    "HomeIconList": 16,
    "HorarioEmpresa_DataCard1": 612,
    "HourValue1": 394,
    "HourValue2": 405,
    "Icon1": 72,
    "Icon1_1": 187,
    "Icon1_10": 442,
    "Icon1_11": 644,
    "Icon1_12": 645,
    "Icon1_13": 596,
    "Icon1_14": 597,
    "Icon1_15": 150,
    "Icon1_2": 188,
    "Icon1_3": 110,
    "Icon1_4": 508,
    "Icon1_5": 511,
    "Icon1_6": 512,
    "Icon1_7": 374,
    "Icon1_8": 375,
    "Icon1_9": 441,
    "Icon2": 105,
    "Icon2_1": 106,
    "Icon2_2": 138,
    "Icon2_3": 139,
    "Icon2_4": 688,
    "Icon2_5": 695,
    "Icon3": 6,
    "Icon4": 7,
    "Identification Number_Column1": 41,
    "Identification Number_DataCard1": 252,
    "Image1": 75,
    "Image1_1": 113,
    "Image1_2": 153,
    "Image2": 12,
    "Image3": 22,
    "Image7": 648,
    "Institucional Vehicle Request": 0,
    "International_DataCard1": 549,
    "InvoiceN_DataCard1": 574,
    "Is_Juridical_DataCard1": 362,
    "Juridical Number_Column1": 42,
    "Juridical Number_DataCard1": 257,
    "Label1": 76,
    "Label1_1": 114,
    "Label1_2": 154,
    "Label10": 378,
    "Label10_1": 380,
    "Label10_2": 377,
    "Label11": 390,
    "Label11_1": 391,
    "Label11_2": 392,
    "Label11_3": 401,
    "Label11_4": 402,
    "Label11_5": 403,
    "Label12": 650,
    "Label12_1": 654,
    "Label12_2": 652,
    "Label12_3": 656,
    "Label12_4": 658,
    "Label12_5": 660,
    "Label12_6": 666,
    "Label12_7": 671,
    "Label12_8": 673,
    "Label12_9": 676,
    "Label13": 649,
    "Label13_1": 675,
    "Label14": 662,
    "Label14_1": 663,
    "Label14_2": 664,
    "Label14_3": 665,
    "Label15": 600,
    "Label16": 115,
    "Label16_1": 116,
    "Label16_10": 158,
    "Label16_11": 159,
    "Label16_12": 160,
    "Label16_13": 161,
    "Label16_14": 162,
    "Label16_2": 117,
    "Label16_3": 118,
    "Label16_4": 119,
    "Label16_5": 120,
    "Label16_6": 121,
    "Label16_7": 155,
    "Label16_8": 156,
    "Label16_9": 157,
    "Label17": 21,
    "Label17_1": 13,
    "Label2": 83,
    "Label2_1": 85,
    "Label2_2": 91,
    "Label2_3": 77,
    "Label2_4": 78,
    "Label2_5": 79,
    "Label2_6": 90,
    "Label2_7": 84,
    "Label3": 89,
    "Label4": 0,
    "Label5": 142,
    "Label5_1": 143,
    "Label5_2": 180,
    "Label5_3": 181,
    "Label6": 11,
    "Label7": 3,
    "Label8": 689,
    "Label9": 379,
    "Label9_1": 376,
    "Last Name_Column1": 30,
    "Last Name_DataCard1": 197,
    "LblAppName1": 71,
    "LblAppName1_1": 5,
    "LblAppName1_10": 149,
    "LblAppName1_2": 186,
    "LblAppName1_3": 109,
    "LblAppName1_4": 507,
    "LblAppName1_5": 510,
    "LblAppName1_6": 15,
    "LblAppName1_7": 373,
    "LblAppName1_8": 440,
    "LblAppName1_9": 595,
    "LblAppName2": 643,
    "LblAppName2_1": 680,
    "List": 0,
    "MaestriaSolicitaServicio_DataCard1": 486,
    "MaestriaSolicitudServicio_DataCard1": 424,
    "Master Degree_Column1": 60,
    "Master Degree_DataCard1": 347,
    "Menu": 0,
    "MenuIcon": 17,
    "MinuteValue1": 396,
    "MinuteValue2": 407,
    "Name_DataCard1": 569,
    "NameSolicitor_Columna1": 64,
    "National_DataCard1": 544,
    "NavMenuList": 18,
    "NombreEmpresa_DataCard1": 607,
    "NombreJefe_DataCard1": 382,
    "NombreJefe_DataCard2": 456,
    "NumeroPersonas_DataCard1": 419,
    "NumeroPersonas_DataCard2": 481,
    "Other Payment Plan_Column1": 52,
    "Other Payment Plan_DataCard1": 307,
    "Payment Plan_Column1": 51,
    "Payment Plan_DataCard1": 302,
    "Payment Rate_Column1": 50,
    "Payment Rate_DataCard1": 297,
    "Payment schedule proposed_Column1": 58,
    "Payment schedule proposed_DataCard1": 342,
    "PaymentRequest": 0,
    "Permanent Residence Addresss_Column1": 37,
    "Permanent Residence Addresss_DataCard1": 222,
    "PersonaContactar_DataCard1": 622,
    "PettyCash_DataCard1": 524,
    "Place will stay_Column1": 56,
    "Place will stay_DataCard1": 352,
    "Preferred Payment Method_Column1": 46,
    "Preferred Payment Method_DataCard1": 277,
    "PurchaseRequest": 0,
    "Purpose_Columna1": 69,
    "RectQuickActionBar1": 70,
    "RectQuickActionBar1_1": 4,
    "RectQuickActionBar1_2": 108,
    "RectQuickActionBar1_3": 14,
    "RectQuickActionBar1_4": 148,
    "RectQuickActionBar2": 185,
    "RectQuickActionBar2_1": 506,
    "RectQuickActionBar2_2": 509,
    "RectQuickActionBar2_3": 372,
    "RectQuickActionBar2_4": 439,
    "RectQuickActionBar2_5": 594,
    "RectQuickActionBar3": 642,
    "RectQuickActionBar3_1": 679,
    "Relacion_DataCard1": 584,
    "Representative´s Name_Column1": 32,
    "Representative´s Name_DataCard1": 207,
    "RequestEquimentExternal": 0,
    "Retiro_DataCard1": 637,
    "Separator1": 395,
    "Separator2": 406,
    "Separator2_1": 107,
    "Separator2_2": 140,
    "Separator2_3": 696,
    "Separator2_4": 178,
    "SIMPE_DataCard1": 519,
    "SolicitudMandados": 0,
    "Start date of services_Column1": 47,
    "Start date of services_DataCard1": 282,
    "StarVisible1": 193,
    "StarVisible10": 238,
    "StarVisible100": 502,
    "StarVisible102": 415,
    "StarVisible11": 243,
    "StarVisible12": 248,
    "StarVisible13": 253,
    "StarVisible14": 258,
    "StarVisible15": 263,
    "StarVisible16": 268,
    "StarVisible17": 273,
    "StarVisible18": 278,
    "StarVisible19": 283,
    "StarVisible2": 198,
    "StarVisible20": 288,
    "StarVisible21": 293,
    "StarVisible22": 298,
    "StarVisible23": 303,
    "StarVisible24": 308,
    "StarVisible25": 313,
    "StarVisible26": 318,
    "StarVisible27": 323,
    "StarVisible28": 353,
    "StarVisible29": 328,
    "StarVisible3": 203,
    "StarVisible30": 338,
    "StarVisible31": 368,
    "StarVisible32": 333,
    "StarVisible33": 343,
    "StarVisible34": 535,
    "StarVisible35": 348,
    "StarVisible36": 358,
    "StarVisible37": 540,
    "StarVisible38": 515,
    "StarVisible39": 520,
    "StarVisible4": 208,
    "StarVisible40": 525,
    "StarVisible41": 530,
    "StarVisible42": 545,
    "StarVisible43": 550,
    "StarVisible44": 555,
    "StarVisible45": 560,
    "StarVisible46": 565,
    "StarVisible47": 570,
    "StarVisible48": 575,
    "StarVisible49": 580,
    "StarVisible5": 213,
    "StarVisible50": 585,
    "StarVisible51": 590,
    "StarVisible52": 604,
    "StarVisible53": 609,
    "StarVisible54": 629,
    "StarVisible55": 619,
    "StarVisible56": 614,
    "StarVisible57": 624,
    "StarVisible58": 634,
    "StarVisible59": 639,
    "StarVisible6": 218,
    "StarVisible60": 363,
    "StarVisible7": 228,
    "StarVisible79": 383,
    "StarVisible8": 233,
    "StarVisible80": 388,
    "StarVisible81": 399,
    "StarVisible82": 410,
    "StarVisible84": 420,
    "StarVisible85": 425,
    "StarVisible86": 430,
    "StarVisible88": 435,
    "StarVisible89": 447,
    "StarVisible9": 223,
    "StarVisible90": 452,
    "StarVisible91": 457,
    "StarVisible92": 462,
    "StarVisible93": 467,
    "StarVisible94": 472,
    "StarVisible95": 477,
    "StarVisible96": 482,
    "StarVisible97": 487,
    "StarVisible98": 492,
    "StarVisible99": 497,
    "State_Columna1": 28,
    "Teaching Days_Column1": 44,
    "Teaching Days_DataCard1": 267,
    "TelefonoEmpresa_DataCard1": 617,
    "Telephone Number_Column1": 34,
    "Telephone Number_DataCard1": 217,
    "TextInput1": 651,
    "TextInput1_1": 653,
    "TextInput1_2": 674,
    "TextInput2": 97,
    "TextInput2_1": 98,
    "TextInput2_10": 682,
    "TextInput2_11": 683,
    "TextInput2_12": 684,
    "TextInput2_13": 685,
    "TextInput2_14": 164,
    "TextInput2_15": 165,
    "TextInput2_16": 166,
    "TextInput2_17": 167,
    "TextInput2_18": 168,
    "TextInput2_19": 169,
    "TextInput2_2": 99,
    "TextInput2_3": 124,
    "TextInput2_4": 125,
    "TextInput2_5": 126,
    "TextInput2_6": 127,
    "TextInput2_7": 128,
    "TextInput2_8": 129,
    "TextInput2_9": 681,
    "TextInput3": 102,
    "TextInput3_1": 103,
    "TextInput3_10": 694,
    "TextInput3_11": 693,
    "TextInput3_12": 172,
    "TextInput3_13": 173,
    "TextInput3_14": 174,
    "TextInput3_15": 177,
    "TextInput3_2": 104,
    "TextInput3_3": 132,
    "TextInput3_4": 133,
    "TextInput3_5": 134,
    "TextInput3_6": 690,
    "TextInput3_7": 137,
    "TextInput3_8": 691,
    "TextInput3_9": 692,
    "TextInput4": 1,
    "TextInput5": 145,
    "TextInput5_1": 146,
    "TextInput5_2": 183,
    "TextInput5_3": 184,
    "TextInput6": 677,
    "TextInput7": 88,
    "TextInput7_1": 80,
    "TextInput7_2": 81,
    "TextInput7_3": 82,
    "TextInput7_4": 95,
    "TextInput7_5": 93,
    "TextInput8": 24,
    "TipoPayment_DataCard1": 564,
    "Title_DataCard1": 192,
    "Title_DataCard2": 534,
    "Title_DataCard3": 602,
    "Title_DataCard5": 446,
    "Title1": 23,
    "Total_Column1": 57,
    "Total_DataCard1": 327,
    "Traveling_Column1": 54,
    "Traveling_DataCard1": 317,
    "TravelRequest": 0,
    "Wire Transfer_DataCard1": 514
  },
  "ResourcesJsonIndices": {
    "Image-Contratos (6)": 1,
    "Image-Contratos (7)": 2,
    "Image-Contratos (8)": 3,
    "Image-SampleImage": 0
  },
  "RuleScreenIdWithoutScreen": {},
  "TemplateVersions": {},
  "VolatileProperties": {
    "AnalysisLoadTime": 5.5175057,
    "ControlCount": {
      "attachments": 4,
      "button": 13,
      "checkbox": 4,
      "combobox": 24,
      "dataCard": 10,
      "dataTable": 2,
      "dataTableColumn": 41,
      "datepicker": 12,
      "dropdown": 6,
      "fluidGrid": 4,
      "form": 5,
      "gallery": 6,
      "galleryTemplate": 6,
      "icon": 28,
      "image": 6,
      "label": 322,
      "rectangle": 17,
      "screen": 13,
      "text": 101,
      "toggleSwitch": 4,
      "typedDataCard": 80
    },
    "DeserializationLoadTime": 12.6550922,
    "ErrorCount": 3
  },
  "WasLocalDatabaseReferencesEmpty": true
}